[{"id": 6203380455, "status": "completed", "name": "build", "started_at": "2022-04-28T00:46:36Z", "completed_at": "2022-04-28T00:46:45Z", "steps": "steps/19403814/2236522406_6203380455.json"}, {"id": 6203383038, "status": "completed", "name": "deploy", "started_at": "2022-04-28T00:46:55Z", "completed_at": "2022-04-28T00:47:04Z", "steps": "steps/19403814/2236522406_6203383038.json"}, {"id": 6203383218, "status": "completed", "name": "report-build-status", "started_at": "2022-04-28T00:46:56Z", "completed_at": "2022-04-28T00:46:59Z", "steps": "steps/19403814/2236522406_6203383218.json"}]