[{"id": 6976241949, "status": "completed", "name": "build", "started_at": "2022-06-21T00:46:41Z", "completed_at": "2022-06-21T00:47:00Z", "steps": "steps/19403814/2532334212_6976241949.json"}, {"id": 6976246779, "status": "completed", "name": "deploy", "started_at": "2022-06-21T00:47:11Z", "completed_at": "2022-06-21T00:47:19Z", "steps": "steps/19403814/2532334212_6976246779.json"}, {"id": 6976246882, "status": "completed", "name": "report-build-status", "started_at": "2022-06-21T00:47:10Z", "completed_at": "2022-06-21T00:47:12Z", "steps": "steps/19403814/2532334212_6976246882.json"}]