[{"id": 7015075120, "status": "completed", "name": "build", "started_at": "2022-06-23T00:46:41Z", "completed_at": "2022-06-23T00:47:01Z", "steps": "steps/19403814/2546034410_7015075120.json"}, {"id": 7015079128, "status": "completed", "name": "deploy", "started_at": "2022-06-23T00:47:11Z", "completed_at": "2022-06-23T00:47:20Z", "steps": "steps/19403814/2546034410_7015079128.json"}, {"id": 7015079204, "status": "completed", "name": "report-build-status", "started_at": "2022-06-23T00:47:12Z", "completed_at": "2022-06-23T00:47:16Z", "steps": "steps/19403814/2546034410_7015079204.json"}]