[{"id": 9328308846, "status": "completed", "name": "Runner-Preparation", "started_at": "2022-11-07T05:48:16Z", "completed_at": "2022-11-07T05:48:17Z", "steps": "steps/11678186/3407876647_9328308846.json"}, {"id": 9328310068, "status": "completed", "name": "Integration-Tests (self-hosted, A10)", "started_at": "2022-11-07T06:01:32Z", "completed_at": "2022-11-07T06:12:13Z", "steps": "steps/11678186/3407876647_9328310068.json"}, {"id": 9328310128, "status": "completed", "name": "Integration-Tests (macos-10.15)", "started_at": "2022-11-07T05:48:31Z", "completed_at": "2022-11-07T05:52:17Z", "steps": "steps/11678186/3407876647_9328310128.json"}]