[{"id": 10695127332, "status": "completed", "name": "Runner-Preparation", "started_at": "2023-01-17T10:27:43Z", "completed_at": "2023-01-17T10:27:45Z", "steps": "steps/11678186/3938314829_10695127332.json"}, {"id": 10695130996, "status": "completed", "name": "Integration-Tests (self-hosted, A10)", "started_at": "2023-01-17T10:27:53Z", "completed_at": "2023-01-17T10:29:35Z", "steps": "steps/11678186/3938314829_10695130996.json"}, {"id": 10695131252, "status": "completed", "name": "Integration-Tests (self-hosted, V100)", "started_at": "2023-01-17T10:27:52Z", "completed_at": "2023-01-17T10:29:54Z", "steps": "steps/11678186/3938314829_10695131252.json"}, {"id": 10695131446, "status": "completed", "name": "Integration-Tests (macos-10.15)", "started_at": "2023-01-17T10:28:00Z", "completed_at": "2023-01-17T10:29:58Z", "steps": "steps/11678186/3938314829_10695131446.json"}]