[{"id": 11484637449, "status": "completed", "name": "Runner-Preparation", "started_at": "2023-02-21T08:33:45Z", "completed_at": "2023-02-21T08:33:47Z", "steps": "steps/11678186/4230703848_11484637449.json"}, {"id": 11484641344, "status": "completed", "name": "Integration-Tests (self-hosted, A100)", "started_at": "2023-02-21T08:33:52Z", "completed_at": "2023-02-21T08:36:54Z", "steps": "steps/11678186/4230703848_11484641344.json"}, {"id": 11484641510, "status": "completed", "name": "Integration-Tests (self-hosted, V100)", "started_at": "2023-02-21T08:33:52Z", "completed_at": "2023-02-21T08:37:11Z", "steps": "steps/11678186/4230703848_11484641510.json"}, {"id": 11484641659, "status": "completed", "name": "Integration-Tests (macos-10.15)", "started_at": "2023-02-21T08:34:01Z", "completed_at": "2023-02-21T08:37:14Z", "steps": "steps/11678186/4230703848_11484641659.json"}]