[{"id": 12033342065, "status": "completed", "name": "Runner-Preparation", "started_at": "2023-03-15T21:05:05Z", "completed_at": "2023-03-15T21:05:08Z", "steps": "steps/11678186/4430931783_12033342065.json"}, {"id": 12033346599, "status": "completed", "name": "Integration-Tests (self-hosted, A100, cuda)", "started_at": "2023-03-15T21:12:38Z", "completed_at": "2023-03-15T21:12:38Z", "steps": "steps/11678186/4430931783_12033346599.json"}, {"id": 12033346935, "status": "completed", "name": "Integration-Tests (self-hosted, V100, cuda)", "started_at": "2023-03-15T21:12:38Z", "completed_at": "2023-03-15T21:12:38Z", "steps": "steps/11678186/4430931783_12033346935.json"}, {"id": 12033347188, "status": "completed", "name": "Integration-Tests (self-hosted, gfx908, rocm)", "started_at": "2023-03-15T21:05:13Z", "completed_at": "2023-03-15T21:08:40Z", "steps": "steps/11678186/4430931783_12033347188.json"}, {"id": 12033347473, "status": "completed", "name": "Integration-Tests (macos-10.15)", "started_at": "2023-03-15T21:05:21Z", "completed_at": "2023-03-15T21:12:37Z", "steps": "steps/11678186/4430931783_12033347473.json"}]