[{"id": 12275896872, "status": "completed", "name": "Runner-Preparation", "started_at": "2023-03-25T18:38:38Z", "completed_at": "2023-03-25T18:38:38Z", "steps": "steps/11678186/4520605650_12275896872.json"}, {"id": 12275897836, "status": "completed", "name": "Integration-Tests (self-hosted, A100)", "started_at": "2023-03-25T18:38:42Z", "completed_at": "2023-03-25T19:07:43Z", "steps": "steps/11678186/4520605650_12275897836.json"}, {"id": 12275897953, "status": "completed", "name": "Integration-Tests (self-hosted, V100)", "started_at": "2023-03-25T18:38:42Z", "completed_at": "2023-03-25T19:17:14Z", "steps": "steps/11678186/4520605650_12275897953.json"}, {"id": 12275898001, "status": "completed", "name": "Integration-Tests (self-hosted, gfx908)", "started_at": "2023-03-25T18:38:43Z", "completed_at": "2023-03-25T18:41:57Z", "steps": "steps/11678186/4520605650_12275898001.json"}, {"id": 12275898052, "status": "completed", "name": "Integration-Tests (macos-10.15)", "started_at": "2023-03-25T18:38:51Z", "completed_at": "2023-03-25T18:48:18Z", "steps": "steps/11678186/4520605650_12275898052.json"}]