[{"id": 12985821057, "status": "completed", "name": "Runner-Preparation", "started_at": "2023-04-24T19:05:27Z", "completed_at": "2023-04-24T19:05:29Z", "steps": "steps/11678186/4789959811_12985821057.json"}, {"id": 12985825336, "status": "completed", "name": "Integration-Tests (self-hosted, A100)", "started_at": "2023-04-24T19:05:33Z", "completed_at": "2023-04-24T19:08:17Z", "steps": "steps/11678186/4789959811_12985825336.json"}, {"id": 12985825558, "status": "completed", "name": "Integration-Tests (self-hosted, V100)", "started_at": "2023-04-24T19:05:33Z", "completed_at": "2023-04-24T19:08:18Z", "steps": "steps/11678186/4789959811_12985825558.json"}, {"id": 12985825767, "status": "completed", "name": "Integration-Tests (self-hosted, gfx908)", "started_at": "2023-04-24T19:05:34Z", "completed_at": "2023-04-24T19:08:01Z", "steps": "steps/11678186/4789959811_12985825767.json"}, {"id": 12985825988, "status": "completed", "name": "Integration-Tests (macos-10.15)", "started_at": "2023-04-24T19:05:43Z", "completed_at": "2023-04-24T19:08:20Z", "steps": "steps/11678186/4789959811_12985825988.json"}]