[{"id": 12993457931, "status": "completed", "name": "Runner-Preparation", "started_at": "2023-04-25T01:48:15Z", "completed_at": "2023-04-25T01:48:15Z", "steps": "steps/11678186/4792799309_12993457931.json"}, {"id": 12993459579, "status": "completed", "name": "Integration-Tests (self-hosted, A100)", "started_at": "2023-04-25T01:50:01Z", "completed_at": "2023-04-25T01:50:01Z", "steps": "steps/11678186/4792799309_12993459579.json"}, {"id": 12993459654, "status": "completed", "name": "Integration-Tests (self-hosted, V100)", "started_at": "2023-04-25T01:50:01Z", "completed_at": "2023-04-25T01:50:01Z", "steps": "steps/11678186/4792799309_12993459654.json"}, {"id": 12993459748, "status": "completed", "name": "Integration-Tests (self-hosted, gfx908)", "started_at": "2023-04-25T01:49:49Z", "completed_at": "2023-04-25T01:50:00Z", "steps": "steps/11678186/4792799309_12993459748.json"}, {"id": 12993459835, "status": "completed", "name": "Integration-Tests (macos-10.15)", "started_at": "2023-04-25T01:48:30Z", "completed_at": "2023-04-25T01:50:22Z", "steps": "steps/11678186/4792799309_12993459835.json"}]