[{"id": 13071720269, "status": "completed", "name": "Runner-Preparation", "started_at": "2023-04-27T14:07:49Z", "completed_at": "2023-04-27T14:07:49Z", "steps": "steps/11678186/4820758793_13071720269.json"}, {"id": 13071724473, "status": "completed", "name": "Integration-Tests (self-hosted, A100)", "started_at": "2023-04-27T14:07:54Z", "completed_at": "2023-04-27T14:31:17Z", "steps": "steps/11678186/4820758793_13071724473.json"}, {"id": 13071724707, "status": "completed", "name": "Integration-Tests (self-hosted, V100)", "started_at": "2023-04-27T14:07:54Z", "completed_at": "2023-04-27T14:33:16Z", "steps": "steps/11678186/4820758793_13071724707.json"}, {"id": 13071724931, "status": "completed", "name": "Integration-Tests (self-hosted, gfx908)", "started_at": "2023-04-27T14:07:55Z", "completed_at": "2023-04-27T14:10:30Z", "steps": "steps/11678186/4820758793_13071724931.json"}, {"id": 13071725149, "status": "completed", "name": "Integration-Tests (macos-10.15)", "started_at": "2023-04-27T14:08:03Z", "completed_at": "2023-04-27T14:16:46Z", "steps": "steps/11678186/4820758793_13071725149.json"}]