[{"id": 13121769619, "status": "completed", "name": "Runner-Preparation", "started_at": "2023-04-29T17:31:12Z", "completed_at": "2023-04-29T17:31:13Z", "steps": "steps/11678186/4839819632_13121769619.json"}, {"id": 13121770451, "status": "completed", "name": "Integration-Tests (self-hosted, A100)", "started_at": "2023-04-29T17:31:23Z", "completed_at": "2023-04-29T17:41:27Z", "steps": "steps/11678186/4839819632_13121770451.json"}, {"id": 13121770510, "status": "completed", "name": "Integration-Tests (self-hosted, V100)", "started_at": "2023-04-29T17:31:17Z", "completed_at": "2023-04-29T17:41:42Z", "steps": "steps/11678186/4839819632_13121770510.json"}, {"id": 13121770552, "status": "completed", "name": "Integration-Tests (self-hosted, gfx908)", "started_at": "2023-04-29T17:31:19Z", "completed_at": "2023-04-29T17:33:50Z", "steps": "steps/11678186/4839819632_13121770552.json"}, {"id": 13121770592, "status": "completed", "name": "Integration-Tests (macos-10.15)", "started_at": "2023-04-29T17:31:26Z", "completed_at": "2023-04-29T17:39:31Z", "steps": "steps/11678186/4839819632_13121770592.json"}]