[{"id": 13147005602, "status": "completed", "name": "Runner-Preparation", "started_at": "2023-05-01T14:42:32Z", "completed_at": "2023-05-01T14:42:32Z", "steps": "steps/11678186/4852072805_13147005602.json"}, {"id": 13147007711, "status": "completed", "name": "Integration-Tests (self-hosted, A100)", "started_at": "2023-05-01T14:42:37Z", "completed_at": "2023-05-01T15:05:06Z", "steps": "steps/11678186/4852072805_13147007711.json"}, {"id": 13147007833, "status": "completed", "name": "Integration-Tests (self-hosted, V100)", "started_at": "2023-05-01T14:42:37Z", "completed_at": "2023-05-01T15:15:07Z", "steps": "steps/11678186/4852072805_13147007833.json"}, {"id": 13147007984, "status": "completed", "name": "Integration-Tests (self-hosted, gfx908)", "started_at": "2023-05-01T14:42:38Z", "completed_at": "2023-05-01T14:45:10Z", "steps": "steps/11678186/4852072805_13147007984.json"}, {"id": 13147008108, "status": "completed", "name": "Integration-Tests (macos-10.15)", "started_at": "2023-05-01T14:42:46Z", "completed_at": "2023-05-01T14:55:01Z", "steps": "steps/11678186/4852072805_13147008108.json"}]