[{"id": 13381194662, "status": "completed", "name": "Integration-Tests (self-hosted, V100)", "started_at": "2023-05-10T17:23:39Z", "completed_at": "2023-05-10T17:57:31Z", "steps": "steps/11678186/4939661546_13381194662.json"}, {"id": 13381230430, "status": "completed", "name": "Integration-Tests (self-hosted, gfx908)", "started_at": "2023-05-10T17:23:00Z", "completed_at": "2023-05-10T17:25:35Z", "steps": "steps/11678186/4939661546_13381230430.json"}, {"id": 13381634695, "status": "completed", "name": "Integration-Tests (self-hosted, A100)", "started_at": "2023-05-10T17:23:23Z", "completed_at": "2023-05-10T17:46:01Z", "steps": "steps/11678186/4939661546_13381634695.json"}]