[{"id": 13936905756, "status": "completed", "name": "Runner-Preparation", "started_at": "2023-06-01T19:08:48Z", "completed_at": "2023-06-01T19:08:50Z", "steps": "steps/11678186/5148263485_13936905756.json"}, {"id": 13936909824, "status": "completed", "name": "Integration-Tests (self-hosted, A100)", "started_at": "2023-06-01T19:08:54Z", "completed_at": "2023-06-01T19:39:33Z", "steps": "steps/11678186/5148263485_13936909824.json"}, {"id": 13936910060, "status": "completed", "name": "Integration-Tests (self-hosted, V100)", "started_at": "2023-06-01T19:08:54Z", "completed_at": "2023-06-01T19:54:34Z", "steps": "steps/11678186/5148263485_13936910060.json"}, {"id": 13936910282, "status": "completed", "name": "Integration-Tests (self-hosted, gfx908)", "started_at": "2023-06-01T19:08:55Z", "completed_at": "2023-06-01T19:12:06Z", "steps": "steps/11678186/5148263485_13936910282.json"}]