[{"id": 14486580421, "status": "completed", "name": "Runner-Preparation", "started_at": "2023-06-22T22:11:09Z", "completed_at": "2023-06-22T22:11:11Z", "steps": "steps/11678186/5350777002_14486580421.json"}, {"id": 14486583795, "status": "completed", "name": "Integration-Tests (self-hosted, A100)", "started_at": "2023-06-22T22:18:34Z", "completed_at": "2023-06-22T22:18:34Z", "steps": "steps/11678186/5350777002_14486583795.json"}, {"id": 14486583937, "status": "completed", "name": "Integration-Tests (self-hosted, V100)", "started_at": "2023-06-22T22:18:34Z", "completed_at": "2023-06-22T22:18:34Z", "steps": "steps/11678186/5350777002_14486583937.json"}, {"id": 14486584074, "status": "completed", "name": "Integration-Tests (self-hosted, H100)", "started_at": "2023-06-22T22:15:03Z", "completed_at": "2023-06-22T22:18:49Z", "steps": "steps/11678186/5350777002_14486584074.json"}, {"id": 14486584222, "status": "completed", "name": "Integration-Tests (self-hosted, gfx908)", "started_at": "2023-06-22T22:11:17Z", "completed_at": "2023-06-22T22:14:28Z", "steps": "steps/11678186/5350777002_14486584222.json"}, {"id": 14486584345, "status": "completed", "name": "Integration-Tests (self-hosted, arc770)", "started_at": "2023-06-22T22:11:17Z", "completed_at": "2023-06-22T22:15:57Z", "steps": "steps/11678186/5350777002_14486584345.json"}]