[{"id": 14623569983, "status": "completed", "name": "Runner-Preparation", "started_at": "2023-06-28T13:02:22Z", "completed_at": "2023-06-28T13:02:22Z", "steps": "steps/11678186/5400157649_14623569983.json"}, {"id": 14623574508, "status": "completed", "name": "Integration-Tests (self-hosted, A100)", "started_at": "2023-06-28T13:36:56Z", "completed_at": "2023-06-28T14:11:57Z", "steps": "steps/11678186/5400157649_14623574508.json"}, {"id": 14623574758, "status": "completed", "name": "Integration-Tests (self-hosted, H100)", "started_at": "2023-06-28T13:24:45Z", "completed_at": "2023-06-28T13:47:30Z", "steps": "steps/11678186/5400157649_14623574758.json"}, {"id": 14623575007, "status": "completed", "name": "Integration-Tests (self-hosted, gfx908)", "started_at": "2023-06-28T13:05:23Z", "completed_at": "2023-06-28T13:08:46Z", "steps": "steps/11678186/5400157649_14623575007.json"}, {"id": 14623575270, "status": "completed", "name": "Integration-Tests (self-hosted, arc770)", "started_at": "2023-06-28T15:23:21Z", "completed_at": "2023-06-28T17:24:03Z", "steps": "steps/11678186/5400157649_14623575270.json"}, {"id": 14631908884, "status": "completed", "name": "Compare-artifacts", "started_at": "2023-06-28T17:24:10Z", "completed_at": "2023-06-28T17:24:41Z", "steps": "steps/11678186/5400157649_14631908884.json"}]