[{"id": 14677131376, "status": "completed", "name": "Runner-Preparation", "started_at": "2023-06-30T05:44:15Z", "completed_at": "2023-06-30T05:44:16Z", "steps": "steps/11678186/5419718293_14677131376.json"}, {"id": 14677133570, "status": "completed", "name": "Integration-Tests (self-hosted, A100)", "started_at": "2023-06-30T05:44:22Z", "completed_at": "2023-06-30T06:19:28Z", "steps": "steps/11678186/5419718293_14677133570.json"}, {"id": 14677133633, "status": "completed", "name": "Integration-Tests (self-hosted, H100)", "started_at": "2023-06-30T05:44:22Z", "completed_at": "2023-06-30T06:07:07Z", "steps": "steps/11678186/5419718293_14677133633.json"}, {"id": 14677133702, "status": "completed", "name": "Integration-Tests (self-hosted, gfx908)", "started_at": "2023-06-30T05:44:24Z", "completed_at": "2023-06-30T05:47:36Z", "steps": "steps/11678186/5419718293_14677133702.json"}, {"id": 14677133806, "status": "completed", "name": "Integration-Tests (self-hosted, arc770)", "started_at": "2023-06-30T05:44:24Z", "completed_at": "2023-06-30T05:49:07Z", "steps": "steps/11678186/5419718293_14677133806.json"}, {"id": 14677676163, "status": "completed", "name": "Compare-artifacts", "started_at": "2023-06-30T06:19:38Z", "completed_at": "2023-06-30T06:20:32Z", "steps": "steps/11678186/5419718293_14677676163.json"}]