[{"id": 14810311355, "status": "completed", "name": "Runner-Preparation", "started_at": "2023-07-05T23:11:39Z", "completed_at": "2023-07-05T23:11:40Z", "steps": "steps/11678186/5469800912_14810311355.json"}, {"id": 14810313764, "status": "completed", "name": "Integration-Tests-Nvidia (self-hosted, A100)", "started_at": "2023-07-05T23:14:50Z", "completed_at": "2023-07-05T23:14:50Z", "steps": "steps/11678186/5469800912_14810313764.json"}, {"id": 14810313888, "status": "completed", "name": "Integration-Tests-Nvidia (self-hosted, H100)", "started_at": "2023-07-05T23:11:45Z", "completed_at": "2023-07-05T23:14:49Z", "steps": "steps/11678186/5469800912_14810313888.json"}, {"id": 14810313991, "status": "completed", "name": "Integration-Tests-Third-Party (self-hosted, gfx908)", "started_at": "2023-07-05T23:11:47Z", "completed_at": "2023-07-05T23:14:58Z", "steps": "steps/11678186/5469800912_14810313991.json"}, {"id": 14810314083, "status": "completed", "name": "Integration-Tests-Third-Party (self-hosted, arc770)", "started_at": "2023-07-05T23:11:47Z", "completed_at": "2023-07-05T23:16:21Z", "steps": "steps/11678186/5469800912_14810314083.json"}, {"id": 14810368235, "status": "completed", "name": "Compare-artifacts", "started_at": "2023-07-05T23:14:50Z", "completed_at": "2023-07-05T23:14:50Z", "steps": "steps/11678186/5469800912_14810368235.json"}]