[{"id": 15011667935, "status": "completed", "name": "Runner-Preparation", "started_at": "2023-07-13T11:44:26Z", "completed_at": "2023-07-13T11:44:27Z", "steps": "steps/11678186/5542665050_15011667935.json"}, {"id": 15011670605, "status": "completed", "name": "Integration-Tests-Third-Party (self-hosted, gfx908)", "started_at": "2023-07-13T11:44:35Z", "completed_at": "2023-07-13T11:47:50Z", "steps": "steps/11678186/5542665050_15011670605.json"}, {"id": 15011670773, "status": "completed", "name": "Integration-Tests-Third-Party (self-hosted, arc770)", "started_at": "2023-07-13T11:44:35Z", "completed_at": "2023-07-13T11:49:11Z", "steps": "steps/11678186/5542665050_15011670773.json"}, {"id": 15011670946, "status": "completed", "name": "Integration-Tests-Nvidia (self-hosted, A100)", "started_at": "2023-07-13T11:44:34Z", "completed_at": "2023-07-13T11:56:30Z", "steps": "steps/11678186/5542665050_15011670946.json"}, {"id": 15011671079, "status": "completed", "name": "Integration-Tests-Nvidia (self-hosted, H100)", "started_at": "2023-07-13T11:44:34Z", "completed_at": "2023-07-13T11:51:06Z", "steps": "steps/11678186/5542665050_15011671079.json"}, {"id": 15011965587, "status": "completed", "name": "Compare-artifacts", "started_at": "2023-07-13T11:56:37Z", "completed_at": "2023-07-13T11:57:39Z", "steps": "steps/11678186/5542665050_15011965587.json"}]