[{"id": 15938168113, "status": "completed", "name": "Runner-Preparation", "started_at": "2023-08-16T10:29:20Z", "completed_at": "2023-08-16T10:29:20Z", "steps": "steps/11678186/5877651648_15938168113.json"}, {"id": 15938173256, "status": "completed", "name": "Integration-Tests-Nvidia (self-hosted, A100)", "started_at": "2023-08-16T10:29:26Z", "completed_at": "2023-08-16T10:33:15Z", "steps": "steps/11678186/5877651648_15938173256.json"}, {"id": 15938173473, "status": "completed", "name": "Integration-Tests-Nvidia (self-hosted, H100)", "started_at": "2023-08-16T10:29:27Z", "completed_at": "2023-08-16T10:32:59Z", "steps": "steps/11678186/5877651648_15938173473.json"}, {"id": 15938284154, "status": "completed", "name": "Compare-artifacts", "started_at": "2023-08-16T10:33:16Z", "completed_at": "2023-08-16T10:33:16Z", "steps": "steps/11678186/5877651648_15938284154.json"}]