[{"id": 15958825470, "status": "completed", "name": "Runner-Preparation", "started_at": "2023-08-16T22:08:11Z", "completed_at": "2023-08-16T22:08:12Z", "steps": "steps/11678186/5884320808_15958825470.json"}, {"id": 15958828460, "status": "completed", "name": "Integration-Tests-Third-Party (self-hosted, gfx908)", "started_at": "2023-08-16T22:08:17Z", "completed_at": "2023-08-16T22:14:43Z", "steps": "steps/11678186/5884320808_15958828460.json"}, {"id": 15958828574, "status": "completed", "name": "Integration-Tests-Third-Party (self-hosted, arc770)", "started_at": "2023-08-16T22:08:19Z", "completed_at": "2023-08-16T22:14:27Z", "steps": "steps/11678186/5884320808_15958828574.json"}, {"id": 15958828920, "status": "completed", "name": "Integration-Tests-Nvidia (self-hosted, A100)", "started_at": "2023-08-16T22:08:16Z", "completed_at": "2023-08-16T22:20:27Z", "steps": "steps/11678186/5884320808_15958828920.json"}, {"id": 15958829101, "status": "completed", "name": "Integration-Tests-Nvidia (self-hosted, H100)", "started_at": "2023-08-16T22:08:17Z", "completed_at": "2023-08-16T22:30:01Z", "steps": "steps/11678186/5884320808_15958829101.json"}, {"id": 15959288078, "status": "completed", "name": "Compare-artifacts", "started_at": "2023-08-16T22:30:10Z", "completed_at": "2023-08-16T22:31:20Z", "steps": "steps/11678186/5884320808_15959288078.json"}]