[{"id": 16316770298, "status": "completed", "name": "Runner-Preparation", "started_at": "2023-08-29T16:56:43Z", "completed_at": "2023-08-29T16:56:44Z", "steps": "steps/11678186/6015251504_16316770298.json"}, {"id": 16316774353, "status": "completed", "name": "Integration-Tests-Nvidia (self-hosted, A100)", "started_at": "2023-08-29T16:56:48Z", "completed_at": "2023-08-29T17:11:01Z", "steps": "steps/11678186/6015251504_16316774353.json"}, {"id": 16316774536, "status": "completed", "name": "Integration-Tests-Nvidia (self-hosted, H100)", "started_at": "2023-08-29T16:56:49Z", "completed_at": "2023-08-29T17:06:27Z", "steps": "steps/11678186/6015251504_16316774536.json"}, {"id": 16316774710, "status": "completed", "name": "Integration-Tests-Third-Party", "started_at": "2023-08-29T16:56:45Z", "completed_at": "2023-08-29T16:56:45Z", "steps": "steps/11678186/6015251504_16316774710.json"}, {"id": 16317226140, "status": "completed", "name": "Compare-artifacts", "started_at": "2023-08-29T17:11:09Z", "completed_at": "2023-08-29T17:11:58Z", "steps": "steps/11678186/6015251504_16317226140.json"}]