[{"name": "Set up job", "status": "completed", "conclusion": "success", "number": 1, "started_at": "2023-07-11T19:10:20.000-05:00", "completed_at": "2023-07-11T19:10:21.000-05:00"}, {"name": "Report Build Status", "status": "completed", "conclusion": "success", "number": 2, "started_at": "2023-07-11T19:10:23.000-05:00", "completed_at": "2023-07-11T19:10:23.000-05:00"}, {"name": "Complete job", "status": "completed", "conclusion": "success", "number": 3, "started_at": "2023-07-11T19:10:22.000-05:00", "completed_at": "2023-07-11T19:10:22.000-05:00"}]