[{"name": "Set up job", "status": "completed", "conclusion": "success", "number": 1, "started_at": "2023-02-21T13:45:18.000-06:00", "completed_at": "2023-02-21T13:45:20.000-06:00"}, {"name": "Checkout", "status": "completed", "conclusion": "success", "number": 2, "started_at": "2023-02-21T13:45:20.000-06:00", "completed_at": "2023-02-21T13:45:21.000-06:00"}, {"name": "Clear cache", "status": "completed", "conclusion": "success", "number": 3, "started_at": "2023-02-21T13:45:21.000-06:00", "completed_at": "2023-02-21T13:45:21.000-06:00"}, {"name": "Update path", "status": "completed", "conclusion": "success", "number": 4, "started_at": "2023-02-21T13:45:21.000-06:00", "completed_at": "2023-02-21T13:45:21.000-06:00"}, {"name": "Check imports", "status": "completed", "conclusion": "success", "number": 5, "started_at": "2023-02-21T13:45:21.000-06:00", "completed_at": "2023-02-21T13:45:22.000-06:00"}, {"name": "Check python style", "status": "completed", "conclusion": "success", "number": 6, "started_at": "2023-02-21T13:45:22.000-06:00", "completed_at": "2023-02-21T13:45:37.000-06:00"}, {"name": "Check cpp style", "status": "completed", "conclusion": "success", "number": 7, "started_at": "2023-02-21T13:45:37.000-06:00", "completed_at": "2023-02-21T13:45:41.000-06:00"}, {"name": "Flake8", "status": "completed", "conclusion": "success", "number": 8, "started_at": "2023-02-21T13:45:42.000-06:00", "completed_at": "2023-02-21T13:45:43.000-06:00"}, {"name": "Install Triton", "status": "completed", "conclusion": "success", "number": 9, "started_at": "2023-02-21T13:45:43.000-06:00", "completed_at": "2023-02-21T13:49:03.000-06:00"}, {"name": "Run lit tests", "status": "completed", "conclusion": "success", "number": 10, "started_at": "2023-02-21T13:49:03.000-06:00", "completed_at": "2023-02-21T13:49:05.000-06:00"}, {"name": "Run python tests", "status": "completed", "conclusion": "success", "number": 11, "started_at": "2023-02-21T13:49:06.000-06:00", "completed_at": "2023-02-21T14:15:07.000-06:00"}, {"name": "Run CXX unittests", "status": "completed", "conclusion": "success", "number": 12, "started_at": "2023-02-21T14:15:07.000-06:00", "completed_at": "2023-02-21T14:15:07.000-06:00"}, {"name": "Post Checkout", "status": "completed", "conclusion": "success", "number": 24, "started_at": "2023-02-21T14:15:09.000-06:00", "completed_at": "2023-02-21T14:15:09.000-06:00"}, {"name": "Complete job", "status": "completed", "conclusion": "success", "number": 25, "started_at": "2023-02-21T14:15:07.000-06:00", "completed_at": "2023-02-21T14:15:07.000-06:00"}]