[{"name": "Set up job", "status": "completed", "conclusion": "success", "number": 1, "started_at": "2023-08-16T16:36:49.000-05:00", "completed_at": "2023-08-16T16:36:49.000-05:00"}, {"name": "Save PR number", "status": "completed", "conclusion": "success", "number": 2, "started_at": "2023-08-16T16:36:49.000-05:00", "completed_at": "2023-08-16T16:36:49.000-05:00"}, {"name": "Run actions/upload-artifact@v3", "status": "completed", "conclusion": "success", "number": 3, "started_at": "2023-08-16T16:36:49.000-05:00", "completed_at": "2023-08-16T16:36:50.000-05:00"}, {"name": "Complete job", "status": "completed", "conclusion": "success", "number": 4, "started_at": "2023-08-16T16:36:50.000-05:00", "completed_at": "2023-08-16T16:36:50.000-05:00"}]