[{"filename": "python/triton/compiler.py", "status": "modified", "additions": 1, "deletions": 1, "changes": 2, "file_content_changes": "@@ -902,7 +902,7 @@ def ttir_to_ttgir(mod, num_warps, num_stages, compute_capability):\n     pm.add_tritongpu_combine_pass(compute_capability)\n     if compute_capability // 10 == 7:\n         # The update_mma_for_volta pass helps to compute some information for MMA encoding specifically for MMAv1\n-        pm.add_triton_gpu_update_mma_for_volta_pass()\n+        pm.add_tritongpu_update_mma_for_volta_pass()\n     pm.add_cse_pass()\n     pm.add_tritongpu_decompose_conversions_pass()\n     pm.add_cse_pass()"}]