[{"filename": "lib/Conversion/TritonToTritonGPU/TritonToTritonGPUPass.cpp", "status": "modified", "additions": 0, "deletions": 5, "changes": 5, "file_content_changes": "@@ -482,8 +482,6 @@ struct TritonPrintPattern : public OpConversionPattern<triton::PrintOp> {\n   LogicalResult\n   matchAndRewrite(triton::PrintOp op, typename triton::PrintOp::Adaptor adaptor,\n                   ConversionPatternRewriter &rewriter) const override {\n-    rewriter.replaceOpWithNewOp<triton::PrintOp>(op, op.getPrefixAttr(),\n-                                                 adaptor.getOperands());\n     addNamedAttrs(rewriter.replaceOpWithNewOp<triton::PrintOp>(\n                       op, op.getPrefixAttr(), adaptor.getOperands()),\n                   adaptor.getAttributes());\n@@ -498,9 +496,6 @@ struct TritonAssertPattern : public OpConversionPattern<triton::AssertOp> {\n   matchAndRewrite(triton::AssertOp op,\n                   typename triton::AssertOp::Adaptor adaptor,\n                   ConversionPatternRewriter &rewriter) const override {\n-    rewriter.replaceOpWithNewOp<triton::AssertOp>(\n-        op, adaptor.getCondition(), op.getMessageAttr(), op.getFileAttr(),\n-        op.getFuncAttr(), op.getLineAttr());\n     addNamedAttrs(rewriter.replaceOpWithNewOp<triton::AssertOp>(\n                       op, adaptor.getCondition(), op.getMessageAttr(),\n                       op.getFileAttr(), op.getFuncAttr(), op.getLineAttr()),"}]