[{"filename": "lib/Conversion/TritonGPUToLLVM/Utility.h", "status": "modified", "additions": 11, "deletions": 3, "changes": 14, "file_content_changes": "@@ -288,9 +288,17 @@ struct RewriteEnvGuard {\n   static Location *kLoc;\n };\n \n-#define OPERATOR_FOR_EACH(__fn)                                                \\\n-  __fn(+, add) __fn(-, sub) __fn(*, mul) __fn(/, udiv) __fn(^, xor_)           \\\n-      __fn(%, urem)\n+\n+// clang-format off\n+#define OPERATOR_FOR_EACH(__fn)  \\\n+  __fn(+, add)   \\\n+  __fn(-, sub)   \\\n+  __fn(*, mul)   \\\n+  __fn(/, udiv)  \\\n+  __fn(^, xor_)  \\\n+  __fn(%, urem)\n+\n+// clang-format on\n \n #define OPERATOR_WITH_VALUE_DECL(opr__, macro__)                               \\\n   Value operator opr__(const Value &a, const Value &b);"}]