[{"filename": ".github/workflows/integration-tests.yml", "status": "modified", "additions": 1, "deletions": 1, "changes": 2, "file_content_changes": "@@ -83,7 +83,7 @@ jobs:\n         if: ${{matrix.runner[2] == 'rocm'}}\n         run: |\n           cd python\n-          pip3 uninstall --yes torch\n+          pip3 uninstall --yes torch torchvision torchaudio\n           pip3 install --force-reinstall torch --extra-index-url https://download.pytorch.org/whl/rocm5.2\n           TRITON_USE_ASSERT_ENABLED_LLVM=TRUE pip3 install -e '.[tests]'\n "}]