[{"filename": "python/test/unit/language/test_core.py", "status": "modified", "additions": 3, "deletions": 3, "changes": 6, "file_content_changes": "@@ -1284,8 +1284,8 @@ def kernel(X, stride_xm, stride_xn,\n                                            [128, 128, 64, 4],\n                                            [64, 128, 128, 4],\n                                            [32, 128, 64, 2],\n-                                           # triggers nvptx/ptxas bug on V100 currently\n-                                           # [128, 128, 64, 2],\n+                                           [32, 32, 16, 4],\n+                                           [128, 128, 64, 2],\n                                            [64, 128, 128, 2]]\n                           for allow_tf32 in [True]\n                           for col_a in [True, False]\n@@ -1438,7 +1438,7 @@ def kernel(X, stride_xm, stride_xk,\n         np.testing.assert_allclose(z_ref, to_numpy(z_tri), rtol=0.01)\n     # make sure ld/st are vectorized\n     ptx = pgm.asm['ptx']\n-    if K > 16 or N > 16 or M > 16:\n+    if (K > 16 or N > 16 or M > 16) and in_dtype != 'int8':\n         # XXX: skip small sizes because they are not vectorized\n         assert 'ld.global.v4' in ptx\n         assert 'st.global.v4' in ptx"}]