[{"filename": "python/test/unit/language/test_core.py", "status": "modified", "additions": 2, "deletions": 2, "changes": 4, "file_content_changes": "@@ -1421,8 +1421,8 @@ def sum_kernel(\n         tl.store(y_ptr, x_sum)\n \n     BLOCK_SIZE = 128\n-    x = np.ones((BLOCK_SIZE, BLOCK_SIZE), dtype=np.long)\n-    y = np.zeros((1,), dtype=np.long)\n+    x = np.ones((BLOCK_SIZE, BLOCK_SIZE), dtype=np.int32)\n+    y = np.zeros((1,), dtype=np.int32)\n     x_tri = torch.tensor(x, device='cuda')\n     y_tri = torch.tensor(y, device='cuda')\n "}]