[{"filename": "python/test/unit/operators/test_matmul.py", "status": "modified", "additions": 1, "deletions": 1, "changes": 2, "file_content_changes": "@@ -89,7 +89,7 @@ def kernel(Y, X, N, BLOCK_SIZE: tl.constexpr):\n                 (128, 256, 32, 1, 8, 2, None, None, None, AT, BT, ADTYPE, BDTYPE),\n                 (32, 64, 32, 1, 1, 2, 64, 128, 32, AT, BT, ADTYPE, BDTYPE),\n                 (128, 128, 32, 8, 4, 2, 256, 256, 128, AT, BT, ADTYPE, BDTYPE),\n-            ] for ADTYPE, BDTYPE in [(\"float8e4b15\", \"float8e5\"),\n+            ] for ADTYPE, BDTYPE in [(\"float8e5\", \"float8e5\"),\n                                      (\"float8e4\", \"float16\"),\n                                      (\"float16\", \"float8e5\"),\n                                      (\"float16\", \"float32\"),"}]