[{"filename": ".github/workflows/compare-artifacts.yml", "status": "modified", "additions": 17, "deletions": 0, "changes": 17, "file_content_changes": "@@ -35,3 +35,20 @@ jobs:\n             });\n             let fs = require('fs');\n             fs.writeFileSync(`${process.env.GITHUB_WORKSPACE}/pr_number.zip`, Buffer.from(download.data));\n+      - name: 'Unzip artifact'\n+        run: unzip pr_number.zip\n+\n+      - name: 'Comment on PR'\n+        uses: actions/github-script@v6\n+        with:\n+          github-token: ${{ secrets.GITHUB_TOKEN }}\n+          script: |\n+            let fs = require('fs');\n+            let issue_number = Number(fs.readFileSync('./pr_number'));\n+            echo $issue_number\n+            await github.rest.issues.createComment({\n+              owner: context.repo.owner,\n+              repo: context.repo.repo,\n+              issue_number: issue_number,\n+              body: 'Thank you for the PR!'\n+            });"}]