[{"filename": "python/triton/runtime/backends/cuda.c", "status": "modified", "additions": 1, "deletions": 6, "changes": 7, "file_content_changes": "@@ -15,12 +15,7 @@ static inline void gpuAssert(CUresult code, const char *file, int line) {\n   }\n }\n \n-#define CUDA_CHECK(ans)                                                        \\\n-  {                                                                            \\\n-    gpuAssert((ans), __FILE__, __LINE__);                                      \\\n-    if (PyErr_Occurred())                                                      \\\n-      return NULL;                                                             \\\n-  }\n+#define CUDA_CHECK(ans) {{ gpuAssert((ans), __FILE__, __LINE__); }}\n \n #define ADD_ENUM_ITEM(value)                                                   \\\n   do {                                                                         \\"}]