[{"filename": ".github/workflows/wheels.yml", "status": "modified", "additions": 2, "deletions": 2, "changes": 4, "file_content_changes": "@@ -34,8 +34,8 @@ jobs:\n         run: |\n           mkdir wheelhouse-1\n           for i in wheelhouse/*; do\n-            python -mwheel unpack $i\n-            python -mwheel pack triton-2.0.0 --build-number 1 --dest-dir wheelhouse-1\n+            python3 -mwheel unpack $i\n+            python3 -mwheel pack triton-2.0.0 --build-number 1 --dest-dir wheelhouse-1\n             rm -rf triton-2.0.0\n           done\n "}]