[{"filename": ".github/workflows/wheels.yml", "status": "modified", "additions": 5, "deletions": 1, "changes": 6, "file_content_changes": "@@ -31,10 +31,14 @@ jobs:\n           python3 -m cibuildwheel python --output-dir wheelhouse\n \n       - name: Append build number\n+        shell: bash\n         run: |\n+          set -ex\n           mkdir -p wheelhouse-1\n+          find wheelhouse -type f\n           for i in $(find wheelhouse -type f); do\n-            python3 -mwheel unpack $i\n+            echo \"Patching $i\"\n+            python3 -mwheel unpack \"$i\"\n             python3 -mwheel pack triton-2.0.0 --build-number 1 --dest-dir wheelhouse-1\n             rm -rf triton-2.0.0\n           done"}]